calc2tex/__init__.py
calc2tex/advanced_calc.py
calc2tex/calc2tex.py
calc2tex/calc_formula.py
calc2tex/calc_unit.py
calc2tex/helpers.py
calc2tex/parse_tex.py
calc2tex/parse_txt.py
calc2tex/settings.py
calc2tex/settings.txt
calc2tex/trigo.py
calc2tex-0.0.4.dist-info/LICENSE.txt
calc2tex-0.0.4.dist-info/METADATA
calc2tex-0.0.4.dist-info/WHEEL
calc2tex-0.0.4.dist-info/top_level.txt
calc2tex-0.0.4.dist-info/RECORD
