Metadata-Version: 2.1
Name: calc2tex
Version: 0.0.4
Summary: Calculating formulas and displaying them in LaTeX
Home-page: https://github.com/stbech/calc2tex
Author: Stefan Becherer
Author-email: becherer.stefan1@gmail.com
License: MIT License
Platform: UNKNOWN
License-File: LICENSE.txt
Requires-Dist: numpy
